{"001": [{"0": [{"timestamp": 1656910270834}, {"Longitude": 0.0}, {"Latitude": 0.0}, {"Velocity": 0.0}]}, {"1": [{"timestamp": 1656910271835}, {"Longitude": 0.0}, {"Latitude": 0.0}, {"Velocity": 0.0}]}, {"2": [{"timestamp": 1656910272836}, {"Longitude": 0.0}, {"Latitude": 0.0}, {"Velocity": 0.0}]}, {"3": [{"timestamp": 1656910273837}, {"Longitude": 0.0}, {"Latitude": 0.0}, {"Velocity": 0.0}]}, {"4": [{"timestamp": 1656910274838}, {"Longitude": 0.0}, {"Latitude": 0.0}, {"Velocity": 0.0}]}, {"5": [{"timestamp": 1656910275839}, {"Longitude": 0.0}, {"Latitude": 0.0}, {"Velocity": 0.0}]}, {"6": [{"timestamp": 1656910277840}, {"Longitude": 0.0}, {"Latitude": 0.0}, {"Velocity": 0.0}]}, {"7": [{"timestamp": 1656910278841}, {"Longitude": 0.0}, {"Latitude": 0.0}, {"Velocity": 0.0}]}, {"8": [{"timestamp": 1656910279842}, {"Longitude": 0.0}, {"Latitude": 0.0}, {"Velocity": 0.0}]}, {"9": [{"timestamp": 1656910280843}, {"Longitude": 0.0}, {"Latitude": 0.0}, {"Velocity": 0.0}]}, {"10": [{"timestamp": 1656910281844}, {"Longitude": 0.0}, {"Latitude": 0.0}, {"Velocity": 0.0}]}, {"11": [{"timestamp": 1656910282845}, {"Longitude": 0.0}, {"Latitude": 0.0}, {"Velocity": 0.0}]}, {"12": [{"timestamp": 1656910283846}, {"Longitude": 0.0}, {"Latitude": 0.0}, {"Velocity": 0.0}]}, {"13": [{"timestamp": 1656910284847}, {"Longitude": 0.0}, {"Latitude": 0.0}, {"Velocity": 0.0}]}, {"14": [{"timestamp": 1656910285848}, {"Longitude": 0.0}, {"Latitude": 0.0}, {"Velocity": 0.0}]}, {"15": [{"timestamp": 1656910286849}, {"Longitude": 0.0}, {"Latitude": 0.0}, {"Velocity": 0.0}]}, {"16": [{"timestamp": 1656910287850}, {"Longitude": 0.0}, {"Latitude": 0.0}, {"Velocity": 0.0}]}, {"17": [{"timestamp": 1656910288851}, {"Longitude": 0.0}, {"Latitude": 0.0}, {"Velocity": 0.0}]}, {"18": [{"timestamp": 1656910289852}, {"Longitude": 0.0}, {"Latitude": 0.0}, {"Velocity": 0.0}]}, {"19": [{"timestamp": 1656910290852}, {"Longitude": 0.0}, {"Latitude": 0.0}, {"Velocity": 0.0}]}, {"20": [{"timestamp": 1656910291853}, {"Longitude": 0.0}, {"Latitude": 0.0}, {"Velocity": 0.0}]}, {"21": [{"timestamp": 1656910292854}, {"Longitude": 0.0}, {"Latitude": 0.0}, {"Velocity": 0.0}]}, {"22": [{"timestamp": 1656910293855}, {"Longitude": 0.0}, {"Latitude": 0.0}, {"Velocity": 0.0}]}, {"23": [{"timestamp": 1656910295857}, {"Longitude": 0.0}, {"Latitude": 0.0}, {"Velocity": 0.0}]}, {"24": [{"timestamp": 1656910296858}, {"Longitude": 0.0}, {"Latitude": 0.0}, {"Velocity": 0.0}]}, {"25": [{"timestamp": 1656910297859}, {"Longitude": 0.0}, {"Latitude": 0.0}, {"Velocity": 0.0}]}, {"26": [{"timestamp": 1656910298860}, {"Longitude": 0.0}, {"Latitude": 0.0}, {"Velocity": 0.0}]}, {"27": [{"timestamp": 1656910299861}, {"Longitude": 0.0}, {"Latitude": 0.0}, {"Velocity": 0.0}]}, {"28": [{"timestamp": 1656910300861}, {"Longitude": 0.0}, {"Latitude": 0.0}, {"Velocity": 0.0}]}, {"29": [{"timestamp": 1656910301862}, {"Longitude": 0.0}, {"Latitude": 0.0}, {"Velocity": 0.0}]}, {"30": [{"timestamp": 1656910302863}, {"Longitude": 0.0}, {"Latitude": 0.0}, {"Velocity": 0.0}]}, {"31": [{"timestamp": 1656910303864}, {"Longitude": 0.0}, {"Latitude": 0.0}, {"Velocity": 0.0}]}, {"32": [{"timestamp": 1656910304865}, {"Longitude": 0.0}, {"Latitude": 0.0}, {"Velocity": 0.0}]}, {"33": [{"timestamp": 1656910305866}, {"Longitude": 0.0}, {"Latitude": 0.0}, {"Velocity": 0.0}]}, {"34": [{"timestamp": 1656910306867}, {"Longitude": 0.0}, {"Latitude": 0.0}, {"Velocity": 0.0}]}, {"35": [{"timestamp": 1656910307868}, {"Longitude": 0.0}, {"Latitude": 0.0}, {"Velocity": 0.0}]}, {"36": [{"timestamp": 1656910308869}, {"Longitude": 0.0}, {"Latitude": 0.0}, {"Velocity": 0.0}]}, {"37": [{"timestamp": 1656910309870}, {"Longitude": 0.0}, {"Latitude": 0.0}, {"Velocity": 0.0}]}, {"38": [{"timestamp": 1656910310870}, {"Longitude": 0.0}, {"Latitude": 0.0}, {"Velocity": 0.0}]}, {"39": [{"timestamp": 1656910311871}, {"Longitude": 0.0}, {"Latitude": 0.0}, {"Velocity": 0.0}]}, {"40": [{"timestamp": 1656910312872}, {"Longitude": 0.0}, {"Latitude": 0.0}, {"Velocity": 0.0}]}, {"41": [{"timestamp": 1656910313873}, {"Longitude": 0.0}, {"Latitude": 0.0}, {"Velocity": 0.0}]}, {"42": [{"timestamp": 1656910315874}, {"Longitude": 0.0}, {"Latitude": 0.0}, {"Velocity": 0.0}]}, {"43": [{"timestamp": 1656910316875}, {"Longitude": 0.0}, {"Latitude": 0.0}, {"Velocity": 0.0}]}, {"44": [{"timestamp": 1656910317876}, {"Longitude": 0.0}, {"Latitude": 0.0}, {"Velocity": 0.0}]}, {"45": [{"timestamp": 1656910318877}, {"Longitude": 0.0}, {"Latitude": 0.0}, {"Velocity": 0.0}]}, {"46": [{"timestamp": 1656910319878}, {"Longitude": 0.0}, {"Latitude": 0.0}, {"Velocity": 0.0}]}, {"47": [{"timestamp": 1656910320879}, {"Longitude": 0.0}, {"Latitude": 0.0}, {"Velocity": 0.0}]}, {"48": [{"timestamp": 1656910321880}, {"Longitude": 0.0}, {"Latitude": 0.0}, {"Velocity": 0.0}]}, {"49": [{"timestamp": 1656910323881}, {"Longitude": 0.0}, {"Latitude": 0.0}, {"Velocity": 0.0}]}, {"50": [{"timestamp": 1656910324882}, {"Longitude": 0.0}, {"Latitude": 0.0}, {"Velocity": 0.0}]}, {"51": [{"timestamp": 1656910325883}, {"Longitude": 0.0}, {"Latitude": 0.0}, {"Velocity": 0.0}]}, {"52": [{"timestamp": 1656910326884}, {"Longitude": 0.0}, {"Latitude": 0.0}, {"Velocity": 0.0}]}, {"53": [{"timestamp": 1656910327885}, {"Longitude": 0.0}, {"Latitude": 0.0}, {"Velocity": 0.0}]}, {"54": [{"timestamp": 1656910328886}, {"Longitude": 0.0}, {"Latitude": 0.0}, {"Velocity": 0.0}]}, {"55": [{"timestamp": 1656910329887}, {"Longitude": 0.0}, {"Latitude": 0.0}, {"Velocity": 0.0}]}, {"56": [{"timestamp": 1656910330888}, {"Longitude": 0.0}, {"Latitude": 0.0}, {"Velocity": 0.0}]}, {"57": [{"timestamp": 1656910331888}, {"Longitude": 0.0}, {"Latitude": 0.0}, {"Velocity": 0.0}]}, {"58": [{"timestamp": 1656910333890}, {"Longitude": 0.0}, {"Latitude": 0.0}, {"Velocity": 0.0}]}, {"59": [{"timestamp": 1656910334890}, {"Longitude": 0.0}, {"Latitude": 0.0}, {"Velocity": 0.0}]}, {"60": [{"timestamp": 1656910335891}, {"Longitude": 0.0}, {"Latitude": 0.0}, {"Velocity": 0.0}]}, {"61": [{"timestamp": 1656910336892}, {"Longitude": 0.0}, {"Latitude": 0.0}, {"Velocity": 0.0}]}, {"62": [{"timestamp": 1656910338892}, {"Longitude": 0.0}, {"Latitude": 0.0}, {"Velocity": 0.0}]}, {"63": [{"timestamp": 1656910339893}, {"Longitude": 0.0}, {"Latitude": 0.0}, {"Velocity": 0.0}]}, {"64": [{"timestamp": 1656910340894}, {"Longitude": 0.0}, {"Latitude": 0.0}, {"Velocity": 0.0}]}, {"65": [{"timestamp": 1656910341894}, {"Longitude": 0.0}, {"Latitude": 0.0}, {"Velocity": 0.0}]}, {"66": [{"timestamp": 1656910342895}, {"Longitude": 0.0}, {"Latitude": 0.0}, {"Velocity": 0.0}]}, {"67": [{"timestamp": 1656910343896}, {"Longitude": 0.0}, {"Latitude": 0.0}, {"Velocity": 0.0}]}, {"68": [{"timestamp": 1656910344896}, {"Longitude": 0.0}, {"Latitude": 0.0}, {"Velocity": 0.0}]}, {"69": [{"timestamp": 1656910345897}, {"Longitude": 0.0}, {"Latitude": 0.0}, {"Velocity": 0.0}]}, {"70": [{"timestamp": 1656910346898}, {"Longitude": 0.0}, {"Latitude": 0.0}, {"Velocity": 0.0}]}, {"71": [{"timestamp": 1656910347899}, {"Longitude": 0.0}, {"Latitude": 0.0}, {"Velocity": 0.0}]}, {"72": [{"timestamp": 1656910348899}, {"Longitude": 0.0}, {"Latitude": 0.0}, {"Velocity": 0.0}]}, {"73": [{"timestamp": 1656910349900}, {"Longitude": 0.0}, {"Latitude": 0.0}, {"Velocity": 0.0}]}, {"74": [{"timestamp": 1656910351901}, {"Longitude": 0.0}, {"Latitude": 0.0}, {"Velocity": 0.0}]}, {"75": [{"timestamp": 1656910352902}, {"Longitude": 0.0}, {"Latitude": 0.0}, {"Velocity": 0.0}]}, {"76": [{"timestamp": 1656910353903}, {"Longitude": 0.0}, {"Latitude": 0.0}, {"Velocity": 0.0}]}, {"77": [{"timestamp": 1656910354903}, {"Longitude": 0.0}, {"Latitude": 0.0}, {"Velocity": 0.0}]}, {"78": [{"timestamp": 1656910355904}, {"Longitude": 0.0}, {"Latitude": 0.0}, {"Velocity": 0.0}]}, {"79": [{"timestamp": 1656910356905}, {"Longitude": 0.0}, {"Latitude": 0.0}, {"Velocity": 0.0}]}, {"80": [{"timestamp": 1656910357905}, {"Longitude": 0.0}, {"Latitude": 0.0}, {"Velocity": 0.0}]}, {"81": [{"timestamp": 1656910358906}, {"Longitude": 0.0}, {"Latitude": 0.0}, {"Velocity": 0.0}]}, {"82": [{"timestamp": 1656910360907}, {"Longitude": 0.0}, {"Latitude": 0.0}, {"Velocity": 0.0}]}, {"83": [{"timestamp": 1656910361908}, {"Longitude": 0.0}, {"Latitude": 0.0}, {"Velocity": 0.0}]}, {"84": [{"timestamp": 1656910362909}, {"Longitude": 0.0}, {"Latitude": 0.0}, {"Velocity": 0.0}]}, {"85": [{"timestamp": 1656910363909}, {"Longitude": 0.0}, {"Latitude": 0.0}, {"Velocity": 0.0}]}, {"86": [{"timestamp": 1656910364910}, {"Longitude": 0.0}, {"Latitude": 0.0}, {"Velocity": 0.0}]}, {"87": [{"timestamp": 1656910365911}, {"Longitude": 0.0}, {"Latitude": 0.0}, {"Velocity": 0.0}]}, {"88": [{"timestamp": 1656910366911}, {"Longitude": 0.0}, {"Latitude": 0.0}, {"Velocity": 0.0}]}, {"89": [{"timestamp": 1656910367912}, {"Longitude": 0.0}, {"Latitude": 0.0}, {"Velocity": 0.0}]}, {"90": [{"timestamp": 1656910368913}, {"Longitude": 0.0}, {"Latitude": 0.0}, {"Velocity": 0.0}]}, {"91": [{"timestamp": 1656910369914}, {"Longitude": 0.0}, {"Latitude": 0.0}, {"Velocity": 0.0}]}, {"92": [{"timestamp": 1656910371915}, {"Longitude": 0.0}, {"Latitude": 0.0}, {"Velocity": 0.0}]}, {"93": [{"timestamp": 1656910372915}, {"Longitude": 0.0}, {"Latitude": 0.0}, {"Velocity": 0.0}]}, {"94": [{"timestamp": 1656910373916}, {"Longitude": 0.0}, {"Latitude": 0.0}, {"Velocity": 0.0}]}, {"95": [{"timestamp": 1656910374917}, {"Longitude": 0.0}, {"Latitude": 0.0}, {"Velocity": 0.0}]}, {"96": [{"timestamp": 1656910375918}, {"Longitude": 0.0}, {"Latitude": 0.0}, {"Velocity": 0.0}]}, {"97": [{"timestamp": 1656910376918}, {"Longitude": 0.0}, {"Latitude": 0.0}, {"Velocity": 0.0}]}, {"98": [{"timestamp": 1656910379920}, {"Longitude": 0.0}, {"Latitude": 0.0}, {"Velocity": 0.0}]}, {"99": [{"timestamp": 1656910380921}, {"Longitude": 0.0}, {"Latitude": 0.0}, {"Velocity": 0.0}]}, {"100": [{"timestamp": 1656910381921}, {"Longitude": 0.0}, {"Latitude": 0.0}, {"Velocity": 0.0}]}, {"101": [{"timestamp": 1656910382922}, {"Longitude": 0.0}, {"Latitude": 0.0}, {"Velocity": 0.0}]}, {"102": [{"timestamp": 1656910383923}, {"Longitude": 0.0}, {"Latitude": 0.0}, {"Velocity": 0.0}]}, {"103": [{"timestamp": 1656910384923}, {"Longitude": 0.0}, {"Latitude": 0.0}, {"Velocity": 0.0}]}, {"104": [{"timestamp": 1656910385924}, {"Longitude": 0.0}, {"Latitude": 0.0}, {"Velocity": 0.0}]}, {"105": [{"timestamp": 1656910386925}, {"Longitude": 0.0}, {"Latitude": 0.0}, {"Velocity": 0.0}]}, {"106": [{"timestamp": 1656910387925}, {"Longitude": 0.0}, {"Latitude": 0.0}, {"Velocity": 0.0}]}, {"107": [{"timestamp": 1656910388926}, {"Longitude": 0.0}, {"Latitude": 0.0}, {"Velocity": 0.0}]}, {"108": [{"timestamp": 1656910389927}, {"Longitude": 0.0}, {"Latitude": 0.0}, {"Velocity": 0.0}]}, {"109": [{"timestamp": 1656910390928}, {"Longitude": 0.0}, {"Latitude": 0.0}, {"Velocity": 0.0}]}, {"110": [{"timestamp": 1656910391928}, {"Longitude": 0.0}, {"Latitude": 0.0}, {"Velocity": 0.0}]}, {"111": [{"timestamp": 1656910392929}, {"Longitude": 0.0}, {"Latitude": 0.0}, {"Velocity": 0.0}]}, {"112": [{"timestamp": 1656910393930}, {"Longitude": 0.0}, {"Latitude": 0.0}, {"Velocity": 0.0}]}, {"113": [{"timestamp": 1656910394931}, {"Longitude": 0.0}, {"Latitude": 0.0}, {"Velocity": 0.0}]}, {"114": [{"timestamp": 1656910395931}, {"Longitude": 0.0}, {"Latitude": 0.0}, {"Velocity": 0.0}]}, {"115": [{"timestamp": 1656910396932}, {"Longitude": 0.0}, {"Latitude": 0.0}, {"Velocity": 0.0}]}, {"116": [{"timestamp": 1656910397933}, {"Longitude": 0.0}, {"Latitude": 0.0}, {"Velocity": 0.0}]}, {"117": [{"timestamp": 1656910398933}, {"Longitude": 0.0}, {"Latitude": 0.0}, {"Velocity": 0.0}]}, {"118": [{"timestamp": 1656910399934}, {"Longitude": 0.0}, {"Latitude": 0.0}, {"Velocity": 0.0}]}, {"119": [{"timestamp": 1656910400935}, {"Longitude": 0.0}, {"Latitude": 0.0}, {"Velocity": 0.0}]}, {"120": [{"timestamp": 1656910401935}, {"Longitude": 0.0}, {"Latitude": 0.0}, {"Velocity": 0.0}]}, {"121": [{"timestamp": 1656910402936}, {"Longitude": 0.0}, {"Latitude": 0.0}, {"Velocity": 0.0}]}, {"122": [{"timestamp": 1656910403937}, {"Longitude": 0.0}, {"Latitude": 0.0}, {"Velocity": 0.0}]}, {"123": [{"timestamp": 1656910404938}, {"Longitude": 0.0}, {"Latitude": 0.0}, {"Velocity": 0.0}]}, {"124": [{"timestamp": 1656910405938}, {"Longitude": 0.0}, {"Latitude": 0.0}, {"Velocity": 0.0}]}, {"125": [{"timestamp": 1656910406939}, {"Longitude": 0.0}, {"Latitude": 0.0}, {"Velocity": 0.0}]}, {"126": [{"timestamp": 1656910407940}, {"Longitude": 0.0}, {"Latitude": 0.0}, {"Velocity": 0.0}]}, {"127": [{"timestamp": 1656910408940}, {"Longitude": 0.0}, {"Latitude": 0.0}, {"Velocity": 0.0}]}, {"128": [{"timestamp": 1656910409941}, {"Longitude": 0.0}, {"Latitude": 0.0}, {"Velocity": 0.0}]}, {"129": [{"timestamp": 1656910410942}, {"Longitude": 0.0}, {"Latitude": 0.0}, {"Velocity": 0.0}]}, {"130": [{"timestamp": 1656910411943}, {"Longitude": 0.0}, {"Latitude": 0.0}, {"Velocity": 0.0}]}, {"131": [{"timestamp": 1656910412943}, {"Longitude": 0.0}, {"Latitude": 0.0}, {"Velocity": 0.0}]}, {"132": [{"timestamp": 1656910413944}, {"Longitude": 0.0}, {"Latitude": 0.0}, {"Velocity": 0.0}]}, {"133": [{"timestamp": 1656910414945}, {"Longitude": 0.0}, {"Latitude": 0.0}, {"Velocity": 0.0}]}, {"134": [{"timestamp": 1656910415946}, {"Longitude": 0.0}, {"Latitude": 0.0}, {"Velocity": 0.0}]}, {"135": [{"timestamp": 1656910416946}, {"Longitude": 0.0}, {"Latitude": 0.0}, {"Velocity": 0.0}]}, {"136": [{"timestamp": 1656910417947}, {"Longitude": 0.0}, {"Latitude": 0.0}, {"Velocity": 0.0}]}, {"137": [{"timestamp": 1656910418948}, {"Longitude": 0.0}, {"Latitude": 0.0}, {"Velocity": 0.0}]}, {"138": [{"timestamp": 1656910419948}, {"Longitude": 0.0}, {"Latitude": 0.0}, {"Velocity": 0.0}]}, {"139": [{"timestamp": 1656910420949}, {"Longitude": 0.0}, {"Latitude": 0.0}, {"Velocity": 0.0}]}, {"140": [{"timestamp": 1656910421950}, {"Longitude": 0.0}, {"Latitude": 0.0}, {"Velocity": 0.0}]}, {"141": [{"timestamp": 1656910422950}, {"Longitude": 0.0}, {"Latitude": 0.0}, {"Velocity": 0.0}]}, {"142": [{"timestamp": 1656910423951}, {"Longitude": 0.0}, {"Latitude": 0.0}, {"Velocity": 0.0}]}, {"143": [{"timestamp": 1656910424952}, {"Longitude": 0.0}, {"Latitude": 0.0}, {"Velocity": 0.0}]}, {"144": [{"timestamp": 1656910425953}, {"Longitude": 0.0}, {"Latitude": 0.0}, {"Velocity": 0.0}]}, {"145": [{"timestamp": 1656910426953}, {"Longitude": 0.0}, {"Latitude": 0.0}, {"Velocity": 0.0}]}, {"146": [{"timestamp": 1656910427954}, {"Longitude": 0.0}, {"Latitude": 0.0}, {"Velocity": 0.0}]}, {"147": [{"timestamp": 1656910428955}, {"Longitude": 0.0}, {"Latitude": 0.0}, {"Velocity": 0.0}]}, {"148": [{"timestamp": 1656910429955}, {"Longitude": 0.0}, {"Latitude": 0.0}, {"Velocity": 0.0}]}, {"149": [{"timestamp": 1656910430956}, {"Longitude": 0.0}, {"Latitude": 0.0}, {"Velocity": 0.0}]}, {"150": [{"timestamp": 1656910431957}, {"Longitude": 0.0}, {"Latitude": 0.0}, {"Velocity": 0.0}]}, {"151": [{"timestamp": 1656910432957}, {"Longitude": 0.0}, {"Latitude": 0.0}, {"Velocity": 0.0}]}, {"152": [{"timestamp": 1656910433958}, {"Longitude": 0.0}, {"Latitude": 0.0}, {"Velocity": 0.0}]}, {"153": [{"timestamp": 1656910434959}, {"Longitude": 0.0}, {"Latitude": 0.0}, {"Velocity": 0.0}]}, {"154": [{"timestamp": 1656910435959}, {"Longitude": 0.0}, {"Latitude": 0.0}, {"Velocity": 0.0}]}, {"155": [{"timestamp": 1656910436960}, {"Longitude": 0.0}, {"Latitude": 0.0}, {"Velocity": 0.0}]}, {"156": [{"timestamp": 1656910437961}, {"Longitude": 0.0}, {"Latitude": 0.0}, {"Velocity": 0.0}]}, {"157": [{"timestamp": 1656910438962}, {"Longitude": 0.0}, {"Latitude": 0.0}, {"Velocity": 0.0}]}, {"158": [{"timestamp": 1656910439962}, {"Longitude": 0.0}, {"Latitude": 0.0}, {"Velocity": 0.0}]}, {"159": [{"timestamp": 1656910440963}, {"Longitude": 0.0}, {"Latitude": 0.0}, {"Velocity": 0.0}]}, {"160": [{"timestamp": 1656910441964}, {"Longitude": 0.0}, {"Latitude": 0.0}, {"Velocity": 0.0}]}, {"161": [{"timestamp": 1656910442964}, {"Longitude": 0.0}, {"Latitude": 0.0}, {"Velocity": 0.0}]}, {"162": [{"timestamp": 1656910443965}, {"Longitude": 0.0}, {"Latitude": 0.0}, {"Velocity": 0.0}]}, {"163": [{"timestamp": 1656910444966}, {"Longitude": 0.0}, {"Latitude": 0.0}, {"Velocity": 0.0}]}, {"164": [{"timestamp": 1656910445966}, {"Longitude": 0.0}, {"Latitude": 0.0}, {"Velocity": 0.0}]}, {"165": [{"timestamp": 1656910446967}, {"Longitude": 0.0}, {"Latitude": 0.0}, {"Velocity": 0.0}]}, {"166": [{"timestamp": 1656910447968}, {"Longitude": 0.0}, {"Latitude": 0.0}, {"Velocity": 0.0}]}, {"167": [{"timestamp": 1656910448968}, {"Longitude": 0.0}, {"Latitude": 0.0}, {"Velocity": 0.0}]}, {"168": [{"timestamp": 1656910449969}, {"Longitude": 0.0}, {"Latitude": 0.0}, {"Velocity": 0.0}]}, {"169": [{"timestamp": 1656910450970}, {"Longitude": 0.0}, {"Latitude": 0.0}, {"Velocity": 0.0}]}, {"170": [{"timestamp": 1656910451971}, {"Longitude": 0.0}, {"Latitude": 0.0}, {"Velocity": 0.0}]}, {"171": [{"timestamp": 1656910452971}, {"Longitude": 0.0}, {"Latitude": 0.0}, {"Velocity": 0.0}]}, {"172": [{"timestamp": 1656910453972}, {"Longitude": 0.0}, {"Latitude": 0.0}, {"Velocity": 0.0}]}, {"173": [{"timestamp": 1656910454973}, {"Longitude": 0.0}, {"Latitude": 0.0}, {"Velocity": 0.0}]}, {"174": [{"timestamp": 1656910455973}, {"Longitude": 0.0}, {"Latitude": 0.0}, {"Velocity": 0.0}]}, {"175": [{"timestamp": 1656910456974}, {"Longitude": 0.0}, {"Latitude": 0.0}, {"Velocity": 0.0}]}, {"176": [{"timestamp": 1656910457975}, {"Longitude": 0.0}, {"Latitude": 0.0}, {"Velocity": 0.0}]}, {"177": [{"timestamp": 1656910458976}, {"Longitude": 0.0}, {"Latitude": 0.0}, {"Velocity": 0.0}]}, {"178": [{"timestamp": 1656910459976}, {"Longitude": 0.0}, {"Latitude": 0.0}, {"Velocity": 0.0}]}, {"179": [{"timestamp": 1656910460977}, {"Longitude": 0.0}, {"Latitude": 0.0}, {"Velocity": 0.0}]}, {"180": [{"timestamp": 1656910461978}, {"Longitude": 0.0}, {"Latitude": 0.0}, {"Velocity": 0.0}]}, {"181": [{"timestamp": 1656910462978}, {"Longitude": 0.0}, {"Latitude": 0.0}, {"Velocity": 0.0}]}, {"182": [{"timestamp": 1656910463979}, {"Longitude": 0.0}, {"Latitude": 0.0}, {"Velocity": 0.0}]}, {"183": [{"timestamp": 1656910464980}, {"Longitude": 0.0}, {"Latitude": 0.0}, {"Velocity": 0.0}]}, {"184": [{"timestamp": 1656910465980}, {"Longitude": 0.0}, {"Latitude": 0.0}, {"Velocity": 0.0}]}, {"185": [{"timestamp": 1656910466981}, {"Longitude": 0.0}, {"Latitude": 0.0}, {"Velocity": 0.0}]}, {"186": [{"timestamp": 1656910467982}, {"Longitude": 0.0}, {"Latitude": 0.0}, {"Velocity": 0.0}]}, {"187": [{"timestamp": 1656910468983}, {"Longitude": 0.0}, {"Latitude": 0.0}, {"Velocity": 0.0}]}, {"188": [{"timestamp": 1656910469983}, {"Longitude": 0.0}, {"Latitude": 0.0}, {"Velocity": 0.0}]}, {"189": [{"timestamp": 1656910470984}, {"Longitude": 0.0}, {"Latitude": 0.0}, {"Velocity": 0.0}]}, {"190": [{"timestamp": 1656910471985}, {"Longitude": 0.0}, {"Latitude": 0.0}, {"Velocity": 0.0}]}, {"191": [{"timestamp": 1656910472985}, {"Longitude": 0.0}, {"Latitude": 0.0}, {"Velocity": 0.0}]}, {"192": [{"timestamp": 1656910473986}, {"Longitude": 0.0}, {"Latitude": 0.0}, {"Velocity": 0.0}]}, {"193": [{"timestamp": 1656910474987}, {"Longitude": 0.0}, {"Latitude": 0.0}, {"Velocity": 0.0}]}, {"194": [{"timestamp": 1656910475988}, {"Longitude": 0.0}, {"Latitude": 0.0}, {"Velocity": 0.0}]}, {"195": [{"timestamp": 1656910476988}, {"Longitude": 0.0}, {"Latitude": 0.0}, {"Velocity": 0.0}]}, {"196": [{"timestamp": 1656910477989}, {"Longitude": 0.0}, {"Latitude": 0.0}, {"Velocity": 0.0}]}, {"197": [{"timestamp": 1656910478990}, {"Longitude": 0.0}, {"Latitude": 0.0}, {"Velocity": 0.0}]}, {"198": [{"timestamp": 1656910479990}, {"Longitude": 0.0}, {"Latitude": 0.0}, {"Velocity": 0.0}]}, {"199": [{"timestamp": 1656910480991}, {"Longitude": 0.0}, {"Latitude": 0.0}, {"Velocity": 0.0}]}, {"200": [{"timestamp": 1656910481991}, {"Longitude": 0.0}, {"Latitude": 0.0}, {"Velocity": 0.0}]}, {"201": [{"timestamp": 1656910482992}, {"Longitude": 0.0}, {"Latitude": 0.0}, {"Velocity": 0.0}]}, {"202": [{"timestamp": 1656910483992}, {"Longitude": 0.0}, {"Latitude": 0.0}, {"Velocity": 0.0}]}, {"203": [{"timestamp": 1656910484993}, {"Longitude": 0.0}, {"Latitude": 0.0}, {"Velocity": 0.0}]}, {"204": [{"timestamp": 1656910485993}, {"Longitude": 0.0}, {"Latitude": 0.0}, {"Velocity": 0.0}]}, {"205": [{"timestamp": 1656910486994}, {"Longitude": 0.0}, {"Latitude": 0.0}, {"Velocity": 0.0}]}, {"206": [{"timestamp": 1656910487994}, {"Longitude": 0.0}, {"Latitude": 0.0}, {"Velocity": 0.0}]}, {"207": [{"timestamp": 1656910488995}, {"Longitude": 0.0}, {"Latitude": 0.0}, {"Velocity": 0.0}]}, {"208": [{"timestamp": 1656910489995}, {"Longitude": 0.0}, {"Latitude": 0.0}, {"Velocity": 0.0}]}, {"209": [{"timestamp": 1656910490996}, {"Longitude": 0.0}, {"Latitude": 0.0}, {"Velocity": 0.0}]}, {"210": [{"timestamp": 1656910491996}, {"Longitude": 0.0}, {"Latitude": 0.0}, {"Velocity": 0.0}]}, {"211": [{"timestamp": 1656910492997}, {"Longitude": 0.0}, {"Latitude": 0.0}, {"Velocity": 0.0}]}, {"212": [{"timestamp": 1656910493997}, {"Longitude": 0.0}, {"Latitude": 0.0}, {"Velocity": 0.0}]}, {"213": [{"timestamp": 1656910494998}, {"Longitude": 0.0}, {"Latitude": 0.0}, {"Velocity": 0.0}]}, {"214": [{"timestamp": 1656910495998}, {"Longitude": 0.0}, {"Latitude": 0.0}, {"Velocity": 0.0}]}, {"215": [{"timestamp": 1656910496999}, {"Longitude": 0.0}, {"Latitude": 0.0}, {"Velocity": 0.0}]}, {"216": [{"timestamp": 1656910497999}, {"Longitude": 0.0}, {"Latitude": 0.0}, {"Velocity": 0.0}]}, {"217": [{"timestamp": 1656910499000}, {"Longitude": 0.0}, {"Latitude": 0.0}, {"Velocity": 0.0}]}, {"218": [{"timestamp": 1656910500000}, {"Longitude": 0.0}, {"Latitude": 0.0}, {"Velocity": 0.0}]}, {"219": [{"timestamp": 1656910501000}, {"Longitude": 0.0}, {"Latitude": 0.0}, {"Velocity": 0.0}]}, {"220": [{"timestamp": 1656910502001}, {"Longitude": 0.0}, {"Latitude": 0.0}, {"Velocity": 0.0}]}, {"221": [{"timestamp": 1656910503001}, {"Longitude": 0.0}, {"Latitude": 0.0}, {"Velocity": 0.0}]}, {"222": [{"timestamp": 1656910504002}, {"Longitude": 0.0}, {"Latitude": 0.0}, {"Velocity": 0.0}]}, {"223": [{"timestamp": 1656910505002}, {"Longitude": 0.0}, {"Latitude": 0.0}, {"Velocity": 0.0}]}, {"224": [{"timestamp": 1656910506003}, {"Longitude": 0.0}, {"Latitude": 0.0}, {"Velocity": 0.0}]}, {"225": [{"timestamp": 1656910507003}, {"Longitude": 0.0}, {"Latitude": 0.0}, {"Velocity": 0.0}]}, {"226": [{"timestamp": 1656910508004}, {"Longitude": 0.0}, {"Latitude": 0.0}, {"Velocity": 0.0}]}, {"227": [{"timestamp": 1656910509004}, {"Longitude": 0.0}, {"Latitude": 0.0}, {"Velocity": 0.0}]}, {"228": [{"timestamp": 1656910510005}, {"Longitude": 0.0}, {"Latitude": 0.0}, {"Velocity": 0.0}]}, {"229": [{"timestamp": 1656910511005}, {"Longitude": 0.0}, {"Latitude": 0.0}, {"Velocity": 0.0}]}, {"230": [{"timestamp": 1656910512006}, {"Longitude": 0.0}, {"Latitude": 0.0}, {"Velocity": 0.0}]}, {"231": [{"timestamp": 1656910513006}, {"Longitude": 0.0}, {"Latitude": 0.0}, {"Velocity": 0.0}]}, {"232": [{"timestamp": 1656910514007}, {"Longitude": 0.0}, {"Latitude": 0.0}, {"Velocity": 0.0}]}, {"233": [{"timestamp": 1656910515007}, {"Longitude": 0.0}, {"Latitude": 0.0}, {"Velocity": 0.0}]}, {"234": [{"timestamp": 1656910516008}, {"Longitude": 0.0}, {"Latitude": 0.0}, {"Velocity": 0.0}]}, {"235": [{"timestamp": 1656910517008}, {"Longitude": 0.0}, {"Latitude": 0.0}, {"Velocity": 0.0}]}, {"236": [{"timestamp": 1656910518009}, {"Longitude": 0.0}, {"Latitude": 0.0}, {"Velocity": 0.0}]}, {"237": [{"timestamp": 1656910519009}, {"Longitude": 0.0}, {"Latitude": 0.0}, {"Velocity": 0.0}]}, {"238": [{"timestamp": 1656910520010}, {"Longitude": 0.0}, {"Latitude": 0.0}, {"Velocity": 0.0}]}, {"239": [{"timestamp": 1656910521010}, {"Longitude": 0.0}, {"Latitude": 0.0}, {"Velocity": 0.0}]}, {"240": [{"timestamp": 1656910522011}, {"Longitude": 0.0}, {"Latitude": 0.0}, {"Velocity": 0.0}]}, {"241": [{"timestamp": 1656910523011}, {"Longitude": 0.0}, {"Latitude": 0.0}, {"Velocity": 0.0}]}, {"242": [{"timestamp": 1656910524012}, {"Longitude": 0.0}, {"Latitude": 0.0}, {"Velocity": 0.0}]}, {"243": [{"timestamp": 1656910525012}, {"Longitude": 0.0}, {"Latitude": 0.0}, {"Velocity": 0.0}]}, {"244": [{"timestamp": 1656910526013}, {"Longitude": 0.0}, {"Latitude": 0.0}, {"Velocity": 0.0}]}, {"245": [{"timestamp": 1656910527013}, {"Longitude": 0.0}, {"Latitude": 0.0}, {"Velocity": 0.0}]}, {"246": [{"timestamp": 1656910528014}, {"Longitude": 0.0}, {"Latitude": 0.0}, {"Velocity": 0.0}]}, {"247": [{"timestamp": 1656910529014}, {"Longitude": 0.0}, {"Latitude": 0.0}, {"Velocity": 0.0}]}, {"248": [{"timestamp": 1656910530015}, {"Longitude": 0.0}, {"Latitude": 0.0}, {"Velocity": 0.0}]}, {"249": [{"timestamp": 1656910531016}, {"Longitude": 0.0}, {"Latitude": 0.0}, {"Velocity": 0.0}]}, {"250": [{"timestamp": 1656910532016}, {"Longitude": 0.0}, {"Latitude": 0.0}, {"Velocity": 0.0}]}, {"251": [{"timestamp": 1656910533017}, {"Longitude": 0.0}, {"Latitude": 0.0}, {"Velocity": 0.0}]}, {"252": [{"timestamp": 1656910534018}, {"Longitude": 0.0}, {"Latitude": 0.0}, {"Velocity": 0.0}]}, {"253": [{"timestamp": 1656910535019}, {"Longitude": 0.0}, {"Latitude": 0.0}, {"Velocity": 0.0}]}, {"254": [{"timestamp": 1656910536019}, {"Longitude": 0.0}, {"Latitude": 0.0}, {"Velocity": 0.0}]}, {"255": [{"timestamp": 1656910537020}, {"Longitude": 0.0}, {"Latitude": 0.0}, {"Velocity": 0.0}]}, {"256": [{"timestamp": 1656910538021}, {"Longitude": 0.0}, {"Latitude": 0.0}, {"Velocity": 0.0}]}, {"257": [{"timestamp": 1656910539022}, {"Longitude": 0.0}, {"Latitude": 0.0}, {"Velocity": 0.0}]}, {"258": [{"timestamp": 1656910540022}, {"Longitude": 0.0}, {"Latitude": 0.0}, {"Velocity": 0.0}]}, {"259": [{"timestamp": 1656910541023}, {"Longitude": 0.0}, {"Latitude": 0.0}, {"Velocity": 0.0}]}, {"260": [{"timestamp": 1656910542024}, {"Longitude": 0.0}, {"Latitude": 0.0}, {"Velocity": 0.0}]}, {"261": [{"timestamp": 1656910543024}, {"Longitude": 0.0}, {"Latitude": 0.0}, {"Velocity": 0.0}]}, {"262": [{"timestamp": 1656910544025}, {"Longitude": 0.0}, {"Latitude": 0.0}, {"Velocity": 0.0}]}, {"263": [{"timestamp": 1656910545026}, {"Longitude": 0.0}, {"Latitude": 0.0}, {"Velocity": 0.0}]}, {"264": [{"timestamp": 1656910546027}, {"Longitude": 0.0}, {"Latitude": 0.0}, {"Velocity": 0.0}]}, {"265": [{"timestamp": 1656910547027}, {"Longitude": 0.0}, {"Latitude": 0.0}, {"Velocity": 0.0}]}, {"266": [{"timestamp": 1656910548028}, {"Longitude": 0.0}, {"Latitude": 0.0}, {"Velocity": 0.0}]}, {"267": [{"timestamp": 1656910549028}, {"Longitude": 0.0}, {"Latitude": 0.0}, {"Velocity": 0.0}]}, {"268": [{"timestamp": 1656910550029}, {"Longitude": 0.0}, {"Latitude": 0.0}, {"Velocity": 0.0}]}, {"269": [{"timestamp": 1656910551030}, {"Longitude": 0.0}, {"Latitude": 0.0}, {"Velocity": 0.0}]}, {"270": [{"timestamp": 1656910552031}, {"Longitude": 0.0}, {"Latitude": 0.0}, {"Velocity": 0.0}]}, {"271": [{"timestamp": 1656910553031}, {"Longitude": 0.0}, {"Latitude": 0.0}, {"Velocity": 0.0}]}, {"272": [{"timestamp": 1656910554032}, {"Longitude": 0.0}, {"Latitude": 0.0}, {"Velocity": 0.0}]}, {"273": [{"timestamp": 1656910555033}, {"Longitude": 0.0}, {"Latitude": 0.0}, {"Velocity": 0.0}]}, {"274": [{"timestamp": 1656910556033}, {"Longitude": 0.0}, {"Latitude": 0.0}, {"Velocity": 0.0}]}, {"275": [{"timestamp": 1656910557034}, {"Longitude": 0.0}, {"Latitude": 0.0}, {"Velocity": 0.0}]}, {"276": [{"timestamp": 1656910558035}, {"Longitude": 0.0}, {"Latitude": 0.0}, {"Velocity": 0.0}]}, {"277": [{"timestamp": 1656910559036}, {"Longitude": 0.0}, {"Latitude": 0.0}, {"Velocity": 0.0}]}, {"278": [{"timestamp": 1656910560036}, {"Longitude": 0.0}, {"Latitude": 0.0}, {"Velocity": 0.0}]}, {"279": [{"timestamp": 1656910561037}, {"Longitude": 0.0}, {"Latitude": 0.0}, {"Velocity": 0.0}]}, {"280": [{"timestamp": 1656910562038}, {"Longitude": 0.0}, {"Latitude": 0.0}, {"Velocity": 0.0}]}, {"281": [{"timestamp": 1656910563038}, {"Longitude": 0.0}, {"Latitude": 0.0}, {"Velocity": 0.0}]}, {"282": [{"timestamp": 1656910564039}, {"Longitude": 0.0}, {"Latitude": 0.0}, {"Velocity": 0.0}]}, {"283": [{"timestamp": 1656910565040}, {"Longitude": 0.0}, {"Latitude": 0.0}, {"Velocity": 0.0}]}, {"284": [{"timestamp": 1656910566041}, {"Longitude": 0.0}, {"Latitude": 0.0}, {"Velocity": 0.0}]}, {"285": [{"timestamp": 1656910567041}, {"Longitude": 0.0}, {"Latitude": 0.0}, {"Velocity": 0.0}]}, {"286": [{"timestamp": 1656910568042}, {"Longitude": 0.0}, {"Latitude": 0.0}, {"Velocity": 0.0}]}, {"287": [{"timestamp": 1656910569043}, {"Longitude": 0.0}, {"Latitude": 0.0}, {"Velocity": 0.0}]}, {"288": [{"timestamp": 1656910570044}, {"Longitude": 0.0}, {"Latitude": 0.0}, {"Velocity": 0.0}]}, {"289": [{"timestamp": 1656910571044}, {"Longitude": 0.0}, {"Latitude": 0.0}, {"Velocity": 0.0}]}, {"290": [{"timestamp": 1656910572045}, {"Longitude": 0.0}, {"Latitude": 0.0}, {"Velocity": 0.0}]}, {"291": [{"timestamp": 1656910573046}, {"Longitude": 0.0}, {"Latitude": 0.0}, {"Velocity": 0.0}]}, {"292": [{"timestamp": 1656910574047}, {"Longitude": 0.0}, {"Latitude": 0.0}, {"Velocity": 0.0}]}, {"293": [{"timestamp": 1656910575047}, {"Longitude": 0.0}, {"Latitude": 0.0}, {"Velocity": 0.0}]}, {"294": [{"timestamp": 1656910576048}, {"Longitude": 0.0}, {"Latitude": 0.0}, {"Velocity": 0.0}]}, {"295": [{"timestamp": 1656910577049}, {"Longitude": 0.0}, {"Latitude": 0.0}, {"Velocity": 0.0}]}, {"296": [{"timestamp": 1656910578049}, {"Longitude": 0.0}, {"Latitude": 0.0}, {"Velocity": 0.0}]}, {"297": [{"timestamp": 1656910579050}, {"Longitude": 0.0}, {"Latitude": 0.0}, {"Velocity": 0.0}]}, {"298": [{"timestamp": 1656910580051}, {"Longitude": 0.0}, {"Latitude": 0.0}, {"Velocity": 0.0}]}, {"299": [{"timestamp": 1656910581052}, {"Longitude": 0.0}, {"Latitude": 0.0}, {"Velocity": 0.0}]}, {"300": [{"timestamp": 1656910582052}, {"Longitude": 0.0}, {"Latitude": 0.0}, {"Velocity": 0.0}]}, {"301": [{"timestamp": 1656910583053}, {"Longitude": 0.0}, {"Latitude": 0.0}, {"Velocity": 0.0}]}, {"302": [{"timestamp": 1656910584054}, {"Longitude": 0.0}, {"Latitude": 0.0}, {"Velocity": 0.0}]}, {"303": [{"timestamp": 1656910585055}, {"Longitude": 0.0}, {"Latitude": 0.0}, {"Velocity": 0.0}]}, {"304": [{"timestamp": 1656910586056}, {"Longitude": 0.0}, {"Latitude": 0.0}, {"Velocity": 0.0}]}, {"305": [{"timestamp": 1656910587056}, {"Longitude": 0.0}, {"Latitude": 0.0}, {"Velocity": 0.0}]}, {"306": [{"timestamp": 1656910588057}, {"Longitude": 0.0}, {"Latitude": 0.0}, {"Velocity": 0.0}]}, {"307": [{"timestamp": 1656910589058}, {"Longitude": 0.0}, {"Latitude": 0.0}, {"Velocity": 0.0}]}, {"308": [{"timestamp": 1656910590059}, {"Longitude": 0.0}, {"Latitude": 0.0}, {"Velocity": 0.0}]}, {"309": [{"timestamp": 1656910591059}, {"Longitude": 0.0}, {"Latitude": 0.0}, {"Velocity": 0.0}]}, {"310": [{"timestamp": 1656910592060}, {"Longitude": 0.0}, {"Latitude": 0.0}, {"Velocity": 0.0}]}, {"311": [{"timestamp": 1656910593061}, {"Longitude": 0.0}, {"Latitude": 0.0}, {"Velocity": 0.0}]}, {"312": [{"timestamp": 1656910594061}, {"Longitude": 0.0}, {"Latitude": 0.0}, {"Velocity": 0.0}]}, {"313": [{"timestamp": 1656910595062}, {"Longitude": 0.0}, {"Latitude": 0.0}, {"Velocity": 0.0}]}, {"314": [{"timestamp": 1656910596063}, {"Longitude": 0.0}, {"Latitude": 0.0}, {"Velocity": 0.0}]}, {"315": [{"timestamp": 1656910597064}, {"Longitude": 0.0}, {"Latitude": 0.0}, {"Velocity": 0.0}]}, {"316": [{"timestamp": 1656910598064}, {"Longitude": 0.0}, {"Latitude": 0.0}, {"Velocity": 0.0}]}]}